LICENSE
MANIFEST.in
README.md
setup.cfg
setup.py
python_quickbooks.egg-info/PKG-INFO
python_quickbooks.egg-info/SOURCES.txt
python_quickbooks.egg-info/dependency_links.txt
python_quickbooks.egg-info/entry_points.txt
python_quickbooks.egg-info/requires.txt
python_quickbooks.egg-info/top_level.txt
quickbooks/__init__.py
quickbooks/batch.py
quickbooks/cdc.py
quickbooks/client.py
quickbooks/exceptions.py
quickbooks/helpers.py
quickbooks/mixins.py
quickbooks/utils.py
quickbooks/objects/__init__.py
quickbooks/objects/account.py
quickbooks/objects/attachable.py
quickbooks/objects/base.py
quickbooks/objects/batchrequest.py
quickbooks/objects/bill.py
quickbooks/objects/billpayment.py
quickbooks/objects/budget.py
quickbooks/objects/changedatacapture.py
quickbooks/objects/company_info.py
quickbooks/objects/companycurrency.py
quickbooks/objects/creditcardpayment.py
quickbooks/objects/creditcardpayment_entity.py
quickbooks/objects/creditmemo.py
quickbooks/objects/customer.py
quickbooks/objects/customertype.py
quickbooks/objects/department.py
quickbooks/objects/deposit.py
quickbooks/objects/detailline.py
quickbooks/objects/employee.py
quickbooks/objects/estimate.py
quickbooks/objects/exchangerate.py
quickbooks/objects/invoice.py
quickbooks/objects/item.py
quickbooks/objects/journalentry.py
quickbooks/objects/payment.py
quickbooks/objects/paymentmethod.py
quickbooks/objects/preferences.py
quickbooks/objects/purchase.py
quickbooks/objects/purchaseorder.py
quickbooks/objects/recurringtransaction.py
quickbooks/objects/refundreceipt.py
quickbooks/objects/salesreceipt.py
quickbooks/objects/tax.py
quickbooks/objects/taxagency.py
quickbooks/objects/taxcode.py
quickbooks/objects/taxrate.py
quickbooks/objects/taxservice.py
quickbooks/objects/term.py
quickbooks/objects/timeactivity.py
quickbooks/objects/trackingclass.py
quickbooks/objects/transfer.py
quickbooks/objects/vendor.py
quickbooks/objects/vendorcredit.py