Metadata-Version: 2.1
Name: python-quickbooks
Version: 0.9.5
Summary: A Python library for accessing the QuickBooks API.
Home-page: https://github.com/ej2/python-quickbooks
Author: Edward Emanuel Jr.
Author-email: edward.emanuel@gmail.com
License: MIT
Keywords: quickbooks,qbo,accounting
Classifier: Development Status :: 3 - Alpha
Classifier: Intended Audience :: Developers
Classifier: License :: OSI Approved :: MIT License
Classifier: Operating System :: OS Independent
Classifier: Programming Language :: Python
Classifier: Programming Language :: Python :: 3.5
Classifier: Programming Language :: Python :: 3.6
Classifier: Programming Language :: Python :: 3.7
Classifier: Programming Language :: Python :: 3.8
Classifier: Programming Language :: Python :: 3.9
Classifier: Programming Language :: Python :: 3.10
License-File: LICENSE
Requires-Dist: setuptools
Requires-Dist: intuit-oauth==1.2.4
Requires-Dist: rauth>=0.7.3
Requires-Dist: requests>=2.31.0
Requires-Dist: simplejson>=3.19.1
Requires-Dist: python-dateutil
